docup
