Metadata-Version: 1.0
Name: DocUp
Version: 0.5
Summary: Documentation Uploader
Home-page: UNKNOWN
Author: Tony Bashi
Author-email: bashia@uvic.ca
License: UNKNOWN
Platform: UNKNOWN
